<?xml version="1.0"?>
<filters>
    <filter>
        <name>TIME</name>
        <type>datetime</type>
        <label>Date (UTC)</label>
        <visualised>true</visualised>
        <excludedFromDownload>false</excludedFromDownload>
        <wmsStartDateName>date</wmsStartDateName>
        <wmsEndDateName>date</wmsEndDateName>
    </filter>
    <filter>
        <name>campaign_name</name>
        <type>string</type>
        <label>Campaign Name</label>
        <visualised>true</visualised>
        <excludedFromDownload>false</excludedFromDownload>
    </filter>
    <filter>
        <name>platform_name</name>
        <type>string</type>
        <label>Platform Name</label>
        <visualised>true</visualised>
        <excludedFromDownload>false</excludedFromDownload>
    </filter>
    <filter>
        <name>media_count</name>
        <type>numeric</type>
        <label>Media Count</label>
        <visualised>true</visualised>
        <excludedFromDownload>false</excludedFromDownload>
    </filter>
    <filter>
        <name>total_annotation_count</name>
        <type>numeric</type>
        <label>Total Annotation Count</label>
        <visualised>true</visualised>
        <excludedFromDownload>false</excludedFromDownload>
    </filter>
    <filter>
        <name>public_annotation_count</name>
        <type>numeric</type>
        <label>Public Annotation Count</label>
        <visualised>true</visualised>
        <excludedFromDownload>false</excludedFromDownload>
    </filter>
</filters>